setup.py
pyczmq/__init__.py
pyczmq/_cffi.py
pyczmq/types.py
pyczmq/zauth.py
pyczmq/zbeacon.py
pyczmq/zcert.py
pyczmq/zcertstore.py
pyczmq/zctx.py
pyczmq/zframe.py
pyczmq/zloop.py
pyczmq/zmq.py
pyczmq/zmsg.py
pyczmq/zpoller.py
pyczmq/zsocket.py
pyczmq/zstr.py
pyczmq.egg-info/PKG-INFO
pyczmq.egg-info/SOURCES.txt
pyczmq.egg-info/dependency_links.txt
pyczmq.egg-info/requires.txt
pyczmq.egg-info/top_level.txt