Metadata-Version: 1.0
Name: pyczmq
Version: 0.0.4
Summary: pyczmq cffi wrapper
Home-page: https://github.com/michelp/pyczmq
Author: Michel Pelletier
Author-email: pelletier.michel@yahoo.com
License: LGPL v3
Platform: UNKNOWN
